todaydiscourse/__init__.py
todaydiscourse/config.py
todaydiscourse/core.py
todaydiscourse/log.py
todaydiscourse-1.0.1.dist-info/LICENSE
todaydiscourse-1.0.1.dist-info/METADATA
todaydiscourse-1.0.1.dist-info/WHEEL
todaydiscourse-1.0.1.dist-info/entry_points.txt
todaydiscourse-1.0.1.dist-info/top_level.txt
todaydiscourse-1.0.1.dist-info/RECORD
