Metadata-Version: 2.1
Name: todaydiscourse
Version: 1.0.1
Summary: 今日所想，对物所评，一语，即可概括。
Author-email: YeyingXingchen <yeyingxingchen@yeah.net>, NoNameGMM <nonamegmm@qq.com>
License: MIT License
Project-URL: Homepage, https://xingchenopensource.github.io/apis/todaydiscourse
Project-URL: Documentation, https://xingchenopensource.github.io/apis/todaydiscourse/
Project-URL: Repository, https://github.com/XingchenOpenSource/TodayDiscourse.git
Project-URL: Bug Tracker, https://github.com/XingchenOpenSource/TodayDiscourse/issues
Keywords: todaydiscourse,discourse,api
Requires-Python: >=3.12
License-File: LICENSE
